armor_mcp/__init__.py
armor_mcp/server.py
armor_mcp/tools/__init__.py
armor_mcp-0.2.1.dist-info/METADATA
armor_mcp-0.2.1.dist-info/WHEEL
armor_mcp-0.2.1.dist-info/entry_points.txt
armor_mcp-0.2.1.dist-info/RECORD
