Metadata-Version: 2.4
Name: armor-mcp
Version: 0.2.1
Summary: AnomalyArmor MCP Server - Data observability tools for AI assistants
Project-URL: Homepage, https://github.com/anomalyarmor/agents
Project-URL: Documentation, https://docs.anomalyarmor.ai/agents
Project-URL: Repository, https://github.com/anomalyarmor/agents
Project-URL: Issues, https://github.com/anomalyarmor/agents/issues
Author-email: AnomalyArmor <support@anomalyarmor.ai>
License: MIT
Keywords: ai,anomalyarmor,claude,data-observability,mcp
Classifier: Development Status :: 4 - Beta
Classifier: Intended Audience :: Developers
Classifier: License :: OSI Approved :: MIT License
Classifier: Programming Language :: Python :: 3
Classifier: Programming Language :: Python :: 3.11
Classifier: Programming Language :: Python :: 3.12
Classifier: Topic :: Software Development :: Libraries :: Python Modules
Requires-Python: >=3.11
Requires-Dist: anomalyarmor-cli>=0.1.0
Requires-Dist: fastmcp>=0.1.0
Provides-Extra: dev
Requires-Dist: pytest-asyncio>=0.21; extra == 'dev'
Requires-Dist: pytest>=7.0; extra == 'dev'
